instaread/__init__.py
instaread/cli.py
instaread/instaread.py
instaread/instapaper/example.py
instaread/instapaper/instapaper.py
instaread/instapaper/setup.py
instaread/read_assets/img/ipicons@2x.png
instaread/read_assets/img/logo-dark@2x.png
instaread/read_assets/img/logo@2x.png
instaread/read_assets/img/premium_notes@2x.png
instaread/read_assets/img/premium_playlist@2x.png
instaread/read_assets/img/premium_search@2x.png
instaread/read_assets/img/premium_speed@2x.png
instaread/read_assets/read_files/Screen Shot 2016-09-27 at 10.54.28 PM.png
instaread/read_assets/read_files/analytics.js
instaread/read_assets/read_files/bc2556d1c1ea2a2d00.js
instaread/read_assets/read_files/bigfoot.min.css
instaread/read_assets/read_files/checkout.js
instaread/read_assets/read_files/dkx1mpq.js
instaread/read_assets/read_files/endstate_spent.png
instaread/read_assets/read_files/endstate_time_saved.png
instaread/read_assets/read_files/endstate_words.png
instaread/read_assets/read_files/geo_script.js
instaread/read_assets/read_files/read.min.css
instaread/read_assets/read_files/read.min.js
instaread/read_assets/read_files/targets.png
instaread/read_assets/read_files/vendor.min.js
instaread/templates/modals.html
instaread/templates/primary_bar.html
instaread/templates/read_template.html
instaread/templates/speed-read.html
instaread/templates/style_font_typekit.html
instaread-0.1.3.dist-info/DESCRIPTION.rst
instaread-0.1.3.dist-info/METADATA
instaread-0.1.3.dist-info/RECORD
instaread-0.1.3.dist-info/WHEEL
instaread-0.1.3.dist-info/entry_points.txt
instaread-0.1.3.dist-info/metadata.json
instaread-0.1.3.dist-info/top_level.txt
