Metadata-Version: 2.0
Name: instaread
Version: 0.1.3
Summary: Fast and minimal CLI application to read Instapaper from terminal
Home-page: https://github.com/anhdat/instaread
Author: Dat Truong
Author-email: mr.anhdat@gmail.com
License: Copyright 2017 Dat Truong
Requires-Dist: docopt
Requires-Dist: jinja2
Requires-Dist: oauth2 (>=1.9.0.post1)
